epub2html/__init__.py
epub2html/__main__.py
epub2html/epub2html.py
epub2html/jquery.min.js
epub2html/template.html
modulename-2.1.0.dist-info/METADATA
modulename-2.1.0.dist-info/WHEEL
modulename-2.1.0.dist-info/entry_points.txt
modulename-2.1.0.dist-info/top_level.txt
modulename-2.1.0.dist-info/RECORD
