Metadata-Version: 2.1
Name: modulename
Version: 2.1.0
Summary: this is a description
Home-page: https://github.com/abhinavsingh/proxy.py
Author: zk
Author-email: mailsforabhinav@gmail.com
License: BSD
Download-URL: https://github.com/abhinavsingh/proxy.py/archive/master.zip
Keywords: best practice for python project
Platform: UNKNOWN
Classifier: Development Status :: 5 - Production/Stable
Classifier: Environment :: Console
Requires-Python: >3.0.0
Requires-Dist: aget (==0.1.17)
Requires-Dist: aiohttp (==3.5.4)
Requires-Dist: aniso8601 (==3.0.2)
Requires-Dist: appnope (==0.1.0)
Requires-Dist: arrow (==0.13.0)
Requires-Dist: asciimatics (==1.11.0)
Requires-Dist: astroid (==2.0.4)
Requires-Dist: async-timeout (==3.0.1)
Requires-Dist: atomicwrites (==1.3.0)
Requires-Dist: attrs (==19.1.0)
Requires-Dist: augment-nd (==0.1.1)
Requires-Dist: autopep8 (==1.4.3)
Requires-Dist: b2 (==1.4.2)
Requires-Dist: b2sdk (==0.1.8)
Requires-Dist: backcall (==0.1.0)
Requires-Dist: baidupcsapi (==0.9.4)
Requires-Dist: beautifulsoup4 (==4.6.0)
Requires-Dist: biopython (==1.76)
Requires-Dist: blessings (==1.7)
Requires-Dist: bpython (==0.18)
Requires-Dist: browser-cookie3 (==0.7.6)
Requires-Dist: browsercookie (==0.7.5)
Requires-Dist: bs4 (==0.0.1)
Requires-Dist: certifi (==2018.4.16)
Requires-Dist: chardet (==3.0.4)
Requires-Dist: click (==6.7)
Requires-Dist: colorama (==0.4.1)
Requires-Dist: coloredlogs (==10.0)
Requires-Dist: cssselect (==1.0.3)
Requires-Dist: curtsies (==0.3.1)
Requires-Dist: cycler (==0.10.0)
Requires-Dist: Cython (==0.29.5)
Requires-Dist: decorator (==4.4.1)
Requires-Dist: defusedxml (==0.5.0)
Requires-Dist: diskcache (==4.0.0)
Requires-Dist: docopt (==0.6.2)
Requires-Dist: dukpy (==0.2.2)
Requires-Dist: entrypoints (==0.3)
Requires-Dist: Flask (==1.0.2)
Requires-Dist: Flask-Cors (==3.0.8)
Requires-Dist: Flask-Login (==0.4.1)
Requires-Dist: Flask-RESTful (==0.3.6)
Requires-Dist: funcsigs (==1.0.2)
Requires-Dist: fuse (==0.1.2)
Requires-Dist: fusepy (==3.0.1)
Requires-Dist: future (==0.17.1)
Requires-Dist: gitdb2 (==2.0.6)
Requires-Dist: GitPython (==3.0.5)
Requires-Dist: glfw (==1.10.1)
Requires-Dist: gospel-pdf (==2.0.8)
Requires-Dist: greenlet (==0.4.15)
Requires-Dist: gunpowder (==0.3.2)
Requires-Dist: h5py (==2.10.0)
Requires-Dist: HTMLParser (==0.0.2)
Requires-Dist: httptools (==0.0.13)
Requires-Dist: humanfriendly (==6.1)
Requires-Dist: idna (==2.6)
Requires-Dist: imageio (==2.6.1)
Requires-Dist: importlib-metadata (==0.23)
Requires-Dist: ipdb (==0.12.3)
Requires-Dist: ipython (==7.12.0)
Requires-Dist: ipython-genutils (==0.2.0)
Requires-Dist: isort (==4.3.4)
Requires-Dist: itsdangerous (==0.24)
Requires-Dist: javascripthon (==0.10)
Requires-Dist: jedi (==0.15.1)
Requires-Dist: Jinja2 (==2.10)
Requires-Dist: jsmin (==2.2.2)
Requires-Dist: jupyter-echarts-pypkg (==0.1.2)
Requires-Dist: keyring (==19.2.0)
Requires-Dist: kiwisolver (==1.1.0)
Requires-Dist: lazy-object-proxy (==1.3.1)
Requires-Dist: lml (==0.0.2)
Requires-Dist: logfury (==0.1.2)
Requires-Dist: lxml (==4.3.3)
Requires-Dist: lz4 (==2.2.1)
Requires-Dist: macropy3 (==1.1.0b2)
Requires-Dist: MarkupSafe (==1.0)
Requires-Dist: matplotlib (==3.1.3)
Requires-Dist: mccabe (==0.6.1)
Requires-Dist: meson (==0.51.2)
Requires-Dist: mkp (==1.0)
Requires-Dist: modulename (==2.1.0)
Requires-Dist: more-itertools (==7.2.0)
Requires-Dist: msgpack (==0.6.1)
Requires-Dist: mugen (==0.4.4)
Requires-Dist: multidict (==4.5.2)
Requires-Dist: mypy (==0.670)
Requires-Dist: mypy-extensions (==0.4.1)
Requires-Dist: nanoget (==1.12.0)
Requires-Dist: nanomath (==0.23.1)
Requires-Dist: NanoPlot (==1.28.2)
Requires-Dist: nanoplotter (==1.10.0)
Requires-Dist: networkx (==2.4)
Requires-Dist: numpy (==1.16.0)
Requires-Dist: onedrivesdk (==1.1.8)
Requires-Dist: packaging (==19.2)
Requires-Dist: pandas (==0.24.1)
Requires-Dist: parso (==0.5.1)
Requires-Dist: patsy (==0.5.1)
Requires-Dist: pauvre (==0.1.86)
Requires-Dist: pbkdf2 (==1.3)
Requires-Dist: pexpect (==4.8.0)
Requires-Dist: pickleshare (==0.7.5)
Requires-Dist: Pillow (==5.3.0)
Requires-Dist: pipreqs (==0.4.10)
Requires-Dist: plotly (==4.5.0)
Requires-Dist: pluggy (==0.13.0)
Requires-Dist: pretty-errors (==1.2.10)
Requires-Dist: progress (==1.5)
Requires-Dist: prompt-toolkit (==3.0.3)
Requires-Dist: protobuf (==3.7.1)
Requires-Dist: psutil (==5.6.7)
Requires-Dist: ptyprocess (==0.6.0)
Requires-Dist: py (==1.8.0)
Requires-Dist: pyaes (==1.6.1)
Requires-Dist: pyasn1 (==0.4.6)
Requires-Dist: pybind11 (==2.4.3)
Requires-Dist: pycodestyle (==2.4.0)
Requires-Dist: pycrypto (==2.6.1)
Requires-Dist: pycurl (==7.43.0.2)
Requires-Dist: pyecharts (==0.5.11)
Requires-Dist: pyecharts-javascripthon (==0.0.6)
Requires-Dist: pyecharts-jupyter-installer (==0.0.3)
Requires-Dist: pyecharts-snapshot (==0.1.8)
Requires-Dist: pyfiglet (==0.8.post1)
Requires-Dist: pyftpdlib (==1.5.4)
Requires-Dist: pyglfw (==0.2.2)
Requires-Dist: Pygments (==2.5.2)
Requires-Dist: pylint (==2.1.1)
Requires-Dist: pynput (==1.4)
Requires-Dist: pynvim (==0.3.2)
Requires-Dist: pyobjc-core (==5.1.1)
Requires-Dist: pyobjc-framework-Cocoa (==5.1.1)
Requires-Dist: pyobjc-framework-Quartz (==5.1.1)
Requires-Dist: PyOpenGL (==3.1.5)
Requires-Dist: PyOpenGL-accelerate (==3.1.5)
Requires-Dist: pyparsing (==2.4.2)
Requires-Dist: PyQt5 (==5.14.1)
Requires-Dist: PyQt5-sip (==12.7.0)
Requires-Dist: pyquery (==1.4.0)
Requires-Dist: pysam (==0.15.4)
Requires-Dist: PySide2 (==5.11.2)
Requires-Dist: PySocks (==1.7.1)
Requires-Dist: pyspider (==0.3.10)
Requires-Dist: pytest (==3.2.2)
Requires-Dist: python-dateutil (==2.8.0)
Requires-Dist: pytz (==2018.5)
Requires-Dist: PyWavelets (==1.1.1)
Requires-Dist: PyYAML (==5.3)
Requires-Dist: qtgui (==0.0.1)
Requires-Dist: requests (==2.20.0)
Requires-Dist: requests-toolbelt (==0.9.1)
Requires-Dist: retrying (==1.3.3)
Requires-Dist: rsa (==4.0)
Requires-Dist: scapy (==2.4.2)
Requires-Dist: scikit-image (==0.16.2)
Requires-Dist: scipy (==1.4.1)
Requires-Dist: seaborn (==0.10.0)
Requires-Dist: sh (==1.12.14)
Requires-Dist: six (==1.11.0)
Requires-Dist: smmap2 (==2.0.5)
Requires-Dist: snakeviz (==2.0.1)
Requires-Dist: statsmodels (==0.11.0)
Requires-Dist: tblib (==1.3.2)
Requires-Dist: termcolor (==1.1.0)
Requires-Dist: tornado (==4.5.3)
Requires-Dist: tqdm (==4.42.1)
Requires-Dist: traitlets (==4.3.3)
Requires-Dist: tuna (==0.3.1)
Requires-Dist: typed-ast (==1.3.1)
Requires-Dist: u-msgpack-python (==2.5.1)
Requires-Dist: urllib3 (==1.22)
Requires-Dist: virtualenv (==16.0.0)
Requires-Dist: wcwidth (==0.1.7)
Requires-Dist: websockets (==6.0)
Requires-Dist: Werkzeug (==0.14.1)
Requires-Dist: wifiphisher (==1.4)
Requires-Dist: wrapt (==1.10.11)
Requires-Dist: WsgiDAV (==3.0.0)
Requires-Dist: xmltodict (==0.12.0)
Requires-Dist: yapf (==0.29.0)
Requires-Dist: yarg (==0.1.9)
Requires-Dist: yarl (==1.3.0)
Requires-Dist: you-get (==0.4.1314)
Requires-Dist: zipp (==0.6.0)
Requires-Dist: zope.interface (==4.6.0)
